{
  "image": {
    "path": "N63E016_0574.png",
    "size": {
      "height": 512,
      "width": 512
    }
  },
  "labels": [
    {
      "elevation": 275,
      "elevation_bbox_pixels": [
        237.5443310777833,
        165.04788015463077,
        30.11686733200881,
        18.637381289961468
      ],
      "contour_line_pixels": [
        [
          0,
          174
        ],
        [
          81,
          174
        ],
        [
          185,
          174
        ],
        [
          288,
          175
        ],
        [
          391,
          175
        ],
        [
          494,
          181
        ],
        [
          512,
          182
        ]
      ]
    }
  ]
}