{
  "image": {
    "path": "N63E016_0704.png",
    "size": {
      "height": 512,
      "width": 512
    }
  },
  "labels": [
    {
      "elevation": 350,
      "elevation_bbox_pixels": [
        292.65066298859585,
        3.896757014704235,
        51.04203411914091,
        28.76125614782177
      ],
      "contour_line_pixels": [
        [
          512,
          59
        ],
        [
          502,
          53
        ],
        [
          502,
          53
        ],
        [
          461,
          25
        ],
        [
          419,
          18
        ],
        [
          418,
          18
        ],
        [
          377,
          14
        ],
        [
          336,
          11
        ],
        [
          294,
          11
        ],
        [
          252,
          6
        ],
        [
          224,
          0
        ]
      ]
    },
    {
      "elevation": 325,
      "elevation_bbox_pixels": [
        287.7256161978474,
        85.98956313072699,
        47.09430651822947,
        27.137872710917236
      ],
      "contour_line_pixels": [
        [
          512,
          149
        ],
        [
          502,
          148
        ],
        [
          461,
          133
        ],
        [
          449,
          123
        ],
        [
          419,
          107
        ],
        [
          377,
          88
        ],
        [
          376,
          88
        ],
        [
          336,
          85
        ],
        [
          315,
          88
        ],
        [
          294,
          92
        ],
        [
          273,
          88
        ],
        [
          252,
          85
        ],
        [
          211,
          80
        ],
        [
          169,
          73
        ],
        [
          128,
          60
        ],
        [
          100,
          53
        ],
        [
          86,
          50
        ],
        [
          44,
          47
        ],
        [
          17,
          53
        ],
        [
          3,
          64
        ],
        [
          0,
          71
        ]
      ]
    },
    {
      "elevation": 300,
      "elevation_bbox_pixels": [
        195.1123613303222,
        186.2884858580594,
        37.944796142834775,
        21.432304738218136
      ],
      "contour_line_pixels": [
        [
          512,
          251
        ],
        [
          502,
          245
        ],
        [
          461,
          228
        ],
        [
          460,
          227
        ],
        [
          419,
          217
        ],
        [
          377,
          212
        ],
        [
          336,
          204
        ],
        [
          294,
          200
        ],
        [
          252,
          200
        ],
        [
          211,
          200
        ],
        [
          169,
          198
        ],
        [
          128,
          196
        ],
        [
          86,
          196
        ],
        [
          44,
          195
        ],
        [
          3,
          196
        ],
        [
          0,
          196
        ]
      ]
    },
    {
      "elevation": 275,
      "elevation_bbox_pixels": [
        172.53355103932194,
        223.08571430309138,
        60.78400144440377,
        35.953229198894974
      ],
      "contour_line_pixels": [
        [
          512,
          307
        ],
        [
          502,
          305
        ],
        [
          488,
          297
        ],
        [
          461,
          282
        ],
        [
          419,
          275
        ],
        [
          377,
          273
        ],
        [
          336,
          271
        ],
        [
          301,
          262
        ],
        [
          294,
          261
        ],
        [
          252,
          253
        ],
        [
          211,
          249
        ],
        [
          169,
          247
        ],
        [
          128,
          242
        ],
        [
          86,
          238
        ],
        [
          44,
          231
        ],
        [
          31,
          227
        ],
        [
          3,
          223
        ],
        [
          0,
          223
        ]
      ]
    },
    {
      "elevation": 275,
      "elevation_bbox_pixels": [
        140.10096213284254,
        492.4128686724399,
        50.238538064554746,
        30.61783383801938
      ],
      "contour_line_pixels": [
        [
          0,
          505
        ],
        [
          3,
          505
        ],
        [
          12,
          507
        ],
        [
          32,
          512
        ]
      ]
    },
    {
      "elevation": 250,
      "elevation_bbox_pixels": [
        210.96724118598144,
        288.53613992818066,
        58.231429282280374,
        35.92828914820416
      ],
      "contour_line_pixels": []
    }
  ]
}