{
  "image": {
    "path": "N63E016_0767.png",
    "size": {
      "height": 512,
      "width": 512
    }
  },
  "labels": [
    {
      "elevation": 275,
      "elevation_bbox_pixels": [
        350.4276529036257,
        449.41691804831225,
        51.04203411914091,
        28.76125614782177
      ],
      "contour_line_pixels": [
        [
          512,
          491
        ],
        [
          505,
          484
        ],
        [
          501,
          456
        ],
        [
          501,
          456
        ],
        [
          501,
          428
        ],
        [
          501,
          427
        ],
        [
          512,
          410
        ]
      ]
    },
    {
      "elevation": 225,
      "elevation_bbox_pixels": [
        307.5029685227652,
        318.1466975570013,
        37.944796142834775,
        21.432304738218193
      ],
      "contour_line_pixels": [
        [
          267,
          512
        ],
        [
          268,
          512
        ],
        [
          268,
          512
        ],
        [
          294,
          501
        ],
        [
          320,
          495
        ],
        [
          346,
          492
        ],
        [
          355,
          484
        ],
        [
          346,
          461
        ],
        [
          342,
          456
        ],
        [
          320,
          436
        ],
        [
          313,
          428
        ],
        [
          313,
          400
        ],
        [
          320,
          392
        ],
        [
          331,
          371
        ],
        [
          346,
          347
        ],
        [
          351,
          343
        ],
        [
          372,
          335
        ],
        [
          398,
          329
        ],
        [
          423,
          325
        ],
        [
          449,
          321
        ],
        [
          475,
          315
        ],
        [
          475,
          315
        ],
        [
          501,
          301
        ],
        [
          512,
          298
        ]
      ]
    },
    {
      "elevation": 200,
      "elevation_bbox_pixels": [
        288.42527680842994,
        245.94089009461027,
        60.53818876240223,
        35.907664680163634
      ],
      "contour_line_pixels": [
        [
          0,
          455
        ],
        [
          9,
          452
        ],
        [
          35,
          443
        ],
        [
          61,
          441
        ],
        [
          87,
          441
        ],
        [
          113,
          441
        ],
        [
          139,
          441
        ],
        [
          165,
          439
        ],
        [
          191,
          435
        ],
        [
          216,
          428
        ],
        [
          216,
          427
        ],
        [
          242,
          400
        ],
        [
          242,
          371
        ],
        [
          242,
          343
        ],
        [
          242,
          343
        ],
        [
          268,
          315
        ],
        [
          268,
          315
        ],
        [
          294,
          297
        ],
        [
          320,
          287
        ],
        [
          320,
          287
        ],
        [
          346,
          280
        ],
        [
          372,
          269
        ],
        [
          397,
          259
        ],
        [
          398,
          259
        ],
        [
          423,
          245
        ],
        [
          449,
          231
        ],
        [
          449,
          231
        ],
        [
          475,
          229
        ],
        [
          501,
          229
        ],
        [
          512,
          229
        ]
      ]
    },
    {
      "elevation": 175,
      "elevation_bbox_pixels": [
        212.0699523685193,
        215.61170389542178,
        50.238538064554746,
        30.61783383801935
      ],
      "contour_line_pixels": [
        [
          0,
          343
        ],
        [
          9,
          343
        ],
        [
          35,
          315
        ],
        [
          35,
          315
        ],
        [
          61,
          301
        ],
        [
          86,
          287
        ],
        [
          87,
          287
        ],
        [
          113,
          269
        ],
        [
          138,
          259
        ],
        [
          139,
          259
        ],
        [
          165,
          248
        ],
        [
          191,
          237
        ],
        [
          216,
          231
        ],
        [
          216,
          231
        ],
        [
          242,
          226
        ],
        [
          268,
          214
        ],
        [
          294,
          209
        ],
        [
          307,
          203
        ],
        [
          320,
          199
        ],
        [
          346,
          185
        ],
        [
          371,
          175
        ],
        [
          372,
          175
        ],
        [
          398,
          168
        ],
        [
          423,
          164
        ],
        [
          449,
          164
        ],
        [
          475,
          165
        ],
        [
          501,
          165
        ],
        [
          512,
          168
        ]
      ]
    },
    {
      "elevation": 150,
      "elevation_bbox_pixels": [
        196.67369245592494,
        2.95117293894657,
        58.231429282280374,
        35.92828914820416
      ],
      "contour_line_pixels": [
        [
          0,
          6
        ],
        [
          9,
          6
        ],
        [
          10,
          7
        ],
        [
          35,
          21
        ],
        [
          61,
          21
        ],
        [
          87,
          21
        ],
        [
          113,
          21
        ],
        [
          139,
          21
        ],
        [
          165,
          21
        ],
        [
          191,
          21
        ],
        [
          216,
          21
        ],
        [
          242,
          21
        ],
        [
          268,
          21
        ],
        [
          294,
          34
        ],
        [
          320,
          34
        ],
        [
          346,
          35
        ],
        [
          372,
          35
        ],
        [
          398,
          35
        ],
        [
          423,
          35
        ],
        [
          449,
          35
        ],
        [
          475,
          35
        ],
        [
          476,
          35
        ],
        [
          501,
          49
        ],
        [
          512,
          52
        ]
      ]
    }
  ]
}